LICENSE
README.md
setup.cfg
setup.py
telebotbuilder/__init__.py
telebotbuilder.egg-info/PKG-INFO
telebotbuilder.egg-info/SOURCES.txt
telebotbuilder.egg-info/dependency_links.txt
telebotbuilder.egg-info/requires.txt
telebotbuilder.egg-info/top_level.txt