Metadata-Version: 2.1
Name: telebotbuilder
Version: 0.0.2
Summary: An aggregate of packages I frequently install when building Telegram bots
Home-page: https://github.com/zeph1997/telebotbuilder
Author: Zeph Ng
Author-email: zephngdev@gmail.com
License: MIT
Download-URL: https://github.com/zeph1997/telebotbuilder/archive/refs/tags/v0.0.2.tar.gz
Keywords: telebot,telegram,bot,chat,chatbot,firebase
Platform: UNKNOWN
Classifier: Development Status :: 3 - Alpha
Classifier: Intended Audience :: Developers
Classifier: Topic :: Software Development :: Build Tools
Classifier: License :: OSI Approved :: MIT License
Classifier: Programming Language :: Python :: 3
Classifier: Programming Language :: Python :: 3.4
Classifier: Programming Language :: Python :: 3.5
Classifier: Programming Language :: Python :: 3.6
Classifier: Programming Language :: Python :: 3.7
Classifier: Programming Language :: Python :: 3.8
Classifier: Programming Language :: Python :: 3.9
License-File: LICENSE
